{"otherData": {},"traceEvents":[{"cat":"function","dur":114315,"name":"glfwInit","ph":"X","pid":0,"tid":1583621920,"ts":720054670785},{"cat":"function","dur":661038,"name":"glfwCreateWindow","ph":"X","pid":0,"tid":1583621920,"ts":720054785436},{"cat":"function","dur":3614,"name":"void __cdecl Hazel::OpenGLContext::Init(void)","ph":"X","pid":0,"tid":1583621920,"ts":720055446688},{"cat":"function","dur":41,"name":"void __cdecl Hazel::WindowsWindow::SetVsync(bool)","ph":"X","pid":0,"tid":1583621920,"ts":720055450584},{"cat":"function","dur":780012,"name":"void __cdecl Hazel::WindowsWindow::Init(struct Hazel::WindowProps &)","ph":"X","pid":0,"tid":1583621920,"ts":720054670773},{"cat":"function","dur":780130,"name":"__cdecl Hazel::WindowsWindow::WindowsWindow(struct Hazel::WindowProps &)","ph":"X","pid":0,"tid":1583621920,"ts":720054670773},{"cat":"function","dur":1135,"name":"void __cdecl Hazel::ImGuiLayer::OnAttach(void)","ph":"X","pid":0,"tid":1583621920,"ts":720055451043},{"cat":"function","dur":1277,"name":"void __cdecl Hazel::Application::PushOverlay(class Hazel::Layer *)","ph":"X","pid":0,"tid":1583621920,"ts":720055451033},{"cat":"function","dur":8,"name":"void __cdecl Hazel::OpenGLRendererAPI::Init(void)","ph":"X","pid":0,"tid":1583621920,"ts":720055452451},{"cat":"function","dur":5,"name":"__cdecl Hazel::OpenGLVertexArray::OpenGLVertexArray(void)","ph":"X","pid":0,"tid":1583621920,"ts":720055452608},{"cat":"function","dur":238,"name":"class std::basic_string<char,struct std::char_traits<char>,class std::allocator<char> > __cdecl Hazel::OpenGLShader::ReadFile(const class std::basic_string<char,struct std::char_traits<char>,class std::allocator<char> > &)","ph":"X","pid":0,"tid":1583621920,"ts":720055452792},{"cat":"function","dur":1,"name":"unsigned int __cdecl Hazel::ShaderTypeFromString(const class std::basic_string<char,struct std::char_traits<char>,class std::allocator<char> > &)","ph":"X","pid":0,"tid":1583621920,"ts":720055453269},{"cat":"function","dur":1,"name":"unsigned int __cdecl Hazel::ShaderTypeFromString(const class std::basic_string<char,struct std::char_traits<char>,class std::allocator<char> > &)","ph":"X","pid":0,"tid":1583621920,"ts":720055453397},{"cat":"function","dur":1,"name":"unsigned int __cdecl Hazel::ShaderTypeFromString(const class std::basic_string<char,struct std::char_traits<char>,class std::allocator<char> > &)","ph":"X","pid":0,"tid":1583621920,"ts":720055453539},{"cat":"function","dur":1,"name":"unsigned int __cdecl Hazel::ShaderTypeFromString(const class std::basic_string<char,struct std::char_traits<char>,class std::allocator<char> > &)","ph":"X","pid":0,"tid":1583621920,"ts":720055453655},{"cat":"function","dur":669,"name":"class std::unordered_map<unsigned int,class std::basic_string<char,struct std::char_traits<char>,class std::allocator<char> >,struct std::hash<unsigned int>,struct std::equal_to<unsigned int>,class std::allocator<struct std::pair<unsigned int const ,class std::basic_string<char,struct std::char_traits<char>,class std::allocator<char> > > > > __cdecl Hazel::OpenGLShader::PreProcess(const class std::basic_string<char,struct std::char_traits<char>,class std::allocator<char> > &)","ph":"X","pid":0,"tid":1583621920,"ts":720055453156},{"cat":"function","dur":546,"name":"void __cdecl Hazel::OpenGLShader::Compile(const class std::unordered_map<unsigned int,class std::basic_string<char,struct std::char_traits<char>,class std::allocator<char> >,struct std::hash<unsigned int>,struct std::equal_to<unsigned int>,class std::allocator<struct std::pair<unsigned int const ,class std::basic_string<char,struct std::char_traits<char>,class std::allocator<char> > > > > &)","ph":"X","pid":0,"tid":1583621920,"ts":720055453942},{"cat":"function","dur":1870,"name":"__cdecl Hazel::OpenGLShader::OpenGLShader(const class std::basic_string<char,struct std::char_traits<char>,class std::allocator<char> > &)","ph":"X","pid":0,"tid":1583621920,"ts":720055452787},{"cat":"function","dur":230,"name":"__cdecl Hazel::OpenGLTexture2D::OpenGLTexture2D(unsigned int,unsigned int)","ph":"X","pid":0,"tid":1583621920,"ts":720055454835},{"cat":"function","dur":2,"name":"void __cdecl Hazel::OpenGLTexture2D::Bind(unsigned int) const","ph":"X","pid":0,"tid":1583621920,"ts":720055455334},{"cat":"function","dur":73,"name":"void __cdecl Hazel::OpenGLTexture2D::SetData(void *,unsigned int)","ph":"X","pid":0,"tid":1583621920,"ts":720055455465},{"cat":"function","dur":152,"name":"__cdecl Hazel::OpenGLVertexBuffer::OpenGLVertexBuffer(float *,unsigned int)","ph":"X","pid":0,"tid":1583621920,"ts":720055455682},{"cat":"function","dur":10,"name":"__cdecl Hazel::OpenGLIndexBuffer::OpenGLIndexBuffer(unsigned int *,unsigned int)","ph":"X","pid":0,"tid":1583621920,"ts":720055455967},{"cat":"function","dur":0,"name":"void __cdecl Hazel::OpenGLIndexBuffer::Bind(void) const","ph":"X","pid":0,"tid":1583621920,"ts":720055456093},{"cat":"function","dur":120,"name":"void __cdecl Hazel::OpenGLVertexArray::SetIndexBuffer(const class std::shared_ptr<class Hazel::IndexBuffer> &)","ph":"X","pid":0,"tid":1583621920,"ts":720055456089},{"cat":"function","dur":1,"name":"void __cdecl Hazel::OpenGLVertexBuffer::Bind(void) const","ph":"X","pid":0,"tid":1583621920,"ts":720055456373},{"cat":"function","dur":138,"name":"void __cdecl Hazel::OpenGLVertexArray::AddVertexBuffer(const class std::shared_ptr<class Hazel::VertexBuffer> &)","ph":"X","pid":0,"tid":1583621920,"ts":720055456370},{"cat":"function","dur":12,"name":"void __cdecl Hazel::OpenGLShader::Bind(void) const","ph":"X","pid":0,"tid":1583621920,"ts":720055456616},{"cat":"function","dur":16,"name":"void __cdecl Hazel::OpenGLShader::SetInt(const class std::basic_string<char,struct std::char_traits<char>,class std::allocator<char> > &,int)","ph":"X","pid":0,"tid":1583621920,"ts":720055456744},{"cat":"function","dur":4300,"name":"void __cdecl Hazel::Renderer2D::Init(void)","ph":"X","pid":0,"tid":1583621920,"ts":720055452575},{"cat":"function","dur":786240,"name":"__cdecl Hazel::Application::Application(void)","ph":"X","pid":0,"tid":1583621920,"ts":720054670748},{"cat":"function","dur":0,"name":"__cdecl Hazel::OrthographicCamera::OrthographicCamera(float,float,float,float)","ph":"X","pid":0,"tid":1583621920,"ts":720055457116},{"cat":"function","dur":316,"name":"stbi_load","ph":"X","pid":0,"tid":1583621920,"ts":720055457261},{"cat":"function","dur":683,"name":"__cdecl Hazel::OpenGLTexture2D::OpenGLTexture2D(const class std::basic_string<char,struct std::char_traits<char>,class std::allocator<char> > &)","ph":"X","pid":0,"tid":1583621920,"ts":720055457260},{"cat":"function","dur":841,"name":"void __cdecl Sandbox2D::OnAttach(void)","ph":"X","pid":0,"tid":1583621920,"ts":720055457252},{"cat":"function","dur":973,"name":"void __cdecl Hazel::Application::PushLayer(class Hazel::Layer *)","ph":"X","pid":0,"tid":1583621920,"ts":720055457238}]}